osmilepipdemo/__init__.py
osmilepipdemo/example.py
pipdemo/__init__.py
pipdemo/example.py
osmilepipdemo-0.0.1.dist-info/LICENSE
osmilepipdemo-0.0.1.dist-info/METADATA
osmilepipdemo-0.0.1.dist-info/WHEEL
osmilepipdemo-0.0.1.dist-info/top_level.txt
osmilepipdemo-0.0.1.dist-info/RECORD
