Metadata-Version: 2.1
Name: osmilepipdemo
Version: 0.0.1
Summary: a pip upload bag
Author-email: OSmile <whghcyx@outlook.com>
Project-URL: Homepage, https://github.com/pypa/sampleproject
Project-URL: Bug Tracker, https://github.com/pypa/sampleproject/issues
Classifier: Programming Language :: Python :: 3
Classifier: License :: OSI Approved :: MIT License
Classifier: Operating System :: OS Independent
Requires-Python: >=3.6
License-File: LICENSE
